SG1AB/__init__.py
SG1AB/libnnfw_api_pybind.py
SG1AB/aarch64/libarm_compute.so
SG1AB/aarch64/libarm_compute_core.so
SG1AB/aarch64/libarm_compute_ex.so
SG1AB/aarch64/libarm_compute_graph.so
SG1AB/aarch64/libbackend_acl_cl.so
SG1AB/aarch64/libbackend_acl_neon.so
SG1AB/aarch64/libbackend_cpu.so
SG1AB/aarch64/libbackend_ruy.so
SG1AB/aarch64/libbackend_train.so
SG1AB/aarch64/libbackend_xnnpack.so
SG1AB/aarch64/libneuralnetworks.so
SG1AB/aarch64/libnnfw-dev.so
SG1AB/aarch64/libnnfw_api_pybind.so
SG1AB/aarch64/libonert_core.so
SG1AB/armv7l/libarm_compute_ex.so
SG1AB/armv7l/libbackend_acl_cl.so
SG1AB/armv7l/libbackend_acl_neon.so
SG1AB/armv7l/libbackend_cpu.so
SG1AB/armv7l/libbackend_gpu_cl.so
SG1AB/armv7l/libbackend_ruy.so
SG1AB/armv7l/libbackend_train.so
SG1AB/armv7l/libbackend_xnnpack.so
SG1AB/armv7l/libneuralnetworks.so
SG1AB/armv7l/libnnfw-dev.so
SG1AB/armv7l/libnnfw_api_pybind.so
SG1AB/armv7l/libonert_core.so
SG1AB/x86_64/libbackend_cpu.so
SG1AB/x86_64/libbackend_ruy.so
SG1AB/x86_64/libbackend_train.so
SG1AB/x86_64/libneuralnetworks.so
SG1AB/x86_64/libnnfw-dev.so
SG1AB/x86_64/libnnfw_api_pybind.so
SG1AB/x86_64/libonert_core.so
SG1AB-1.0.3.5.dist-info/METADATA
SG1AB-1.0.3.5.dist-info/WHEEL
SG1AB-1.0.3.5.dist-info/top_level.txt
SG1AB-1.0.3.5.dist-info/RECORD
