Metadata-Version: 2.1
Name: SG1AB
Version: 1.0.3.5
Summary: nnfw_api binding
Home-page: https://github.com/Samsung/ONE/tree/master/runtime
Author: Your Name
Author-email: your@email.com
License: Samsung
Platform: UNKNOWN
Requires-Dist: libhdf5-dev
